cgdms/__init__.py
cgdms/cgdms.py
cgdms/cgdms_params_ep45.pt
cgdms-0.1.1.data/scripts/cgdms
cgdms-0.1.1.dist-info/LICENSE
cgdms-0.1.1.dist-info/METADATA
cgdms-0.1.1.dist-info/WHEEL
cgdms-0.1.1.dist-info/top_level.txt
cgdms-0.1.1.dist-info/RECORD
