Metadata-Version: 2.1
Name: cgdms
Version: 0.1.1
Summary: Differentiable molecular simulation of proteins with a coarse-grained potential
Home-page: https://github.com/psipred/cgdms
Author: Joe G Greener
Author-email: j.greener@ucl.ac.uk
License: MIT
Keywords: protein potential force-field coarse-grained automatic-differentiation
Platform: UNKNOWN
Classifier: Programming Language :: Python :: 3
Classifier: License :: OSI Approved :: MIT License
Classifier: Operating System :: OS Independent
Classifier: Topic :: Scientific/Engineering :: Bio-Informatics
Requires-Dist: numpy
Requires-Dist: biopython
Requires-Dist: PeptideBuilder
